winscr.py
Windows_Screensaver-1.1.1.dist-info/LICENSE
Windows_Screensaver-1.1.1.dist-info/METADATA
Windows_Screensaver-1.1.1.dist-info/WHEEL
Windows_Screensaver-1.1.1.dist-info/top_level.txt
Windows_Screensaver-1.1.1.dist-info/RECORD
